chatwoot_api/__init__.py
chatwoot_api/py.typed
chatwoot_api/settings.py
chatwoot_api/sql/get_user_token.sql
chatwoot_api-0.0.4.dist-info/METADATA
chatwoot_api-0.0.4.dist-info/WHEEL
chatwoot_api-0.0.4.dist-info/RECORD
