Metadata-Version: 2.4
Name: chatwoot-api
Version: 0.0.4
Summary: Add your description here
Author-email: SavioR0 <saviorodrigues012@gmail.com>
Requires-Python: >=3.13
Requires-Dist: asyncpg>=0.30.0
Requires-Dist: httpx>=0.28.1
Requires-Dist: pydantic-settings>=2.7.1
Requires-Dist: pydantic>=2.10.6
